dynamic_models/__init__.py
dynamic_models/apps.py
dynamic_models/exceptions.py
dynamic_models/factory.py
dynamic_models/models.py
dynamic_models/schema.py
dynamic_models/utils.py
dynamic_models/migrations/0001_initial.py
dynamic_models/migrations/__init__.py
settings/__init__.py
settings/base.py
settings/dummy.py
settings/postgres.py
tests/__init__.py
tests/conftest.py
tests/models.py
tests/test_factory.py
tests/test_models.py
tests/test_schema_editor.py
tests/test_utils.py
tests/migrations/0001_initial.py
tests/migrations/__init__.py
django_dynamic_models_readonly-0.1.1.dist-info/LICENSE
django_dynamic_models_readonly-0.1.1.dist-info/METADATA
django_dynamic_models_readonly-0.1.1.dist-info/WHEEL
django_dynamic_models_readonly-0.1.1.dist-info/top_level.txt
django_dynamic_models_readonly-0.1.1.dist-info/RECORD
