Metadata-Version: 2.1
Name: django-dynamic-models-readonly
Version: 0.1.1
Summary: Allow dynamic creation and updates to database schema at runtime.
Home-page: https://github.com/abbas123456/django-dynamic-models-readonly
Author: Mohammad Abbas
Author-email: mohammad.abbas86@gmail.com
License: MIT
Platform: UNKNOWN
Classifier: Intended Audience :: Developers
Classifier: License :: OSI Approved :: MIT License
Classifier: Operating System :: OS Independent
Classifier: Programming Language :: Python :: 3
Classifier: Programming Language :: Python :: 3.7
Classifier: Framework :: Django
Requires-Dist: Django (>=2.0)
